gamepp/__init__.py
gamepp/common/__init__.py
gamepp/common/game_object.py
gamepp/patterns/__init__.py
gamepp/patterns/bytecode.py
gamepp/patterns/command.py
gamepp/patterns/component.py
gamepp/patterns/csm.py
gamepp/patterns/data_locality.py
gamepp/patterns/dirty_flag.py
gamepp/patterns/double_buffer.py
gamepp/patterns/event_queue.py
gamepp/patterns/flyweight.py
gamepp/patterns/fsm.py
gamepp/patterns/game_loop.c
gamepp/patterns/game_loop.h
gamepp/patterns/game_loop.py
gamepp/patterns/game_loop_example.c
gamepp/patterns/game_loop_example.exe
gamepp/patterns/gameloop_ext.c
gamepp/patterns/hsm.py
gamepp/patterns/interpreter.py
gamepp/patterns/object_pool.py
gamepp/patterns/observer.py
gamepp/patterns/pda.py
gamepp/patterns/prototype.py
gamepp/patterns/service_locator.py
gamepp/patterns/singleton.py
gamepp/patterns/spatial_partition.py
gamepp/patterns/type_object.py
gamepp/patterns/update_method.py
gamepp-0.3.0.dist-info/METADATA
gamepp-0.3.0.dist-info/WHEEL
gamepp-0.3.0.dist-info/licenses/LICENSE
gamepp-0.3.0.dist-info/RECORD
