Metadata-Version: 2.4
Name: gamepp
Version: 0.3.0
Summary: Various game programming patterns.
Project-URL: Homepage, https://github.com/BillSchumacher/GameProgrammingPatterns
Project-URL: Bug Tracker, https://github.com/BillSchumacher/GameProgrammingPatterns/issues
Author-email: Bill Schumacher <34168009+BillSchumacher@users.noreply.github.com>
License-Expression: MIT
License-File: LICENSE
Classifier: Development Status :: 4 - Beta
Classifier: Operating System :: OS Independent
Classifier: Programming Language :: Python :: 3 :: Only
Classifier: Programming Language :: Python :: 3.10
Classifier: Programming Language :: Python :: 3.11
Requires-Python: >=3.10
